prep/__init__.py
prep/dataset.py
matthewflegg_mbti-0.0.1.dist-info/LICENSE
matthewflegg_mbti-0.0.1.dist-info/METADATA
matthewflegg_mbti-0.0.1.dist-info/WHEEL
matthewflegg_mbti-0.0.1.dist-info/top_level.txt
matthewflegg_mbti-0.0.1.dist-info/RECORD
